odoo/addons/sm_maintenance/__init__.py
odoo/addons/sm_maintenance/__manifest__.py
odoo/addons/sm_maintenance/demo_sommobilitat_config.json
odoo/addons/sm_maintenance/models/__init__.py
odoo/addons/sm_maintenance/models/mail_server.py
odoo/addons/sm_maintenance/models/models_load_data.py
odoo/addons/sm_maintenance/models/models_sm_resources.py
odoo/addons/sm_maintenance/models/models_sm_successful_actions_message.py
odoo/addons/sm_maintenance/models/models_sm_utils.py
odoo/addons/sm_maintenance/security/ir.model.access.csv
odoo/addons/sm_maintenance/views/views_successful_action_message.xml
odoo11_addon_sm_maintenance-11.0.0.0.1.dist-info/METADATA
odoo11_addon_sm_maintenance-11.0.0.0.1.dist-info/WHEEL
odoo11_addon_sm_maintenance-11.0.0.0.1.dist-info/top_level.txt
odoo11_addon_sm_maintenance-11.0.0.0.1.dist-info/RECORD
