Metadata-Version: 2.1
Name: odoo11-addon-sm-maintenance
Version: 11.0.0.0.1
Summary: Module containing a set of sm_maintenance tasks to be executed periodically and keep database entries and sm services healthy
Home-page: https://www.sommobilitat.coop
Author: Som Mobilitat
License: UNKNOWN
Platform: UNKNOWN
Classifier: Programming Language :: Python
Classifier: Framework :: Odoo
Requires-Python: >=2.7, !=3.0.*, !=3.1.*, !=3.2.*, !=3.3.*, !=3.4.*
Requires-Dist: odoo11-addon-sm-connect
Requires-Dist: odoo (<11.1dev,>=11.0a)
